[
    {
        "type": "block",
        "position": [
            -2.0,
            0.0,
            0.0
        ],
        "texture": "white_cube.png",
        "colour": [
            1.0,
            1.0,
            1.0
        ],
        "rotation": [
            -0.0,
            -0.0,
            0.0
        ],
        "scale": [
            1.0,
            1.0,
            1.0
        ]
    },
    {
        "type": "block",
        "position": [
            -2.0,
            1.0,
            0.0
        ],
        "texture": "white_cube.png",
        "colour": [
            1.0,
            1.0,
            1.0
        ],
        "rotation": [
            -0.0,
            -0.0,
            0.0
        ],
        "scale": [
            1.0,
            1.0,
            1.0
        ]
    },
    {
        "type": "enemy",
        "position": [
            -2.0,
            3.0,
            0.0
        ],
        "hp": 100,
        "enemy_type": "default",
        "rotation_y": -0.0
    }
]